arrnounced/__init__.py
arrnounced/announce_parser.py
arrnounced/announcement.py
arrnounced/backend.py
arrnounced/cli.py
arrnounced/config.py
arrnounced/db.py
arrnounced/eventloop_utils.py
arrnounced/irc.py
arrnounced/irc_modes.py
arrnounced/log.py
arrnounced/manager.py
arrnounced/message_handler.py
arrnounced/session_provider.py
arrnounced/tracker.py
arrnounced/tracker_xml_config.py
arrnounced/utils.py
arrnounced/web_handler.py
arrnounced/webui.py
arrnounced/templates/index.html
arrnounced/templates/login.html
arrnounced/templates/logs.html
arrnounced/templates/status.html
arrnounced/templates/assets/bootstrap/css/bootstrap.min.css
arrnounced/templates/assets/bootstrap/fonts/glyphicons-halflings-regular.eot
arrnounced/templates/assets/bootstrap/fonts/glyphicons-halflings-regular.svg
arrnounced/templates/assets/bootstrap/fonts/glyphicons-halflings-regular.ttf
arrnounced/templates/assets/bootstrap/fonts/glyphicons-halflings-regular.woff
arrnounced/templates/assets/bootstrap/fonts/glyphicons-halflings-regular.woff2
arrnounced/templates/assets/bootstrap/js/bootstrap.min.js
arrnounced/templates/assets/css/index.css
arrnounced/templates/assets/css/status.css
arrnounced/templates/assets/css/styles.min.css
arrnounced/templates/assets/css/toastr.css
arrnounced/templates/assets/css/toastr.min.css
arrnounced/templates/assets/css/user.css
arrnounced/templates/assets/js/common.js
arrnounced/templates/assets/js/index.js
arrnounced/templates/assets/js/jquery.min.js
arrnounced/templates/assets/js/jquery.twbsPagination.min.js
arrnounced/templates/assets/js/logs.js
arrnounced/templates/assets/js/script.min.js
arrnounced/templates/assets/js/settings.js
arrnounced/templates/assets/js/toastr.js
arrnounced-0.9.1.dist-info/METADATA
arrnounced-0.9.1.dist-info/WHEEL
arrnounced-0.9.1.dist-info/entry_points.txt
arrnounced-0.9.1.dist-info/top_level.txt
arrnounced-0.9.1.dist-info/RECORD
