Metadata-Version: 2.1
Name: arrnounced
Version: 0.9.1
Summary: Notify Sonarr/Radarr/Lidarr of tracker IRC announcements
Author-email: WeAnnounce <weannounce@protonmail.com>
Project-URL: homepage, https://github.com/weannounce/arrnounced
Requires-Python: <3.10,>=3.7
Requires-Dist: Flask-Login ~=0.6.3
Requires-Dist: Flask-SocketIO ~=5.3.6
Requires-Dist: Flask ~=3.0.3
Requires-Dist: aiohttp ~=3.9.3
Requires-Dist: defusedxml ~=0.7.1
Requires-Dist: pony ~=0.7.17
Requires-Dist: pydle ~=0.9.4
Requires-Dist: tomlkit ~=0.12.4
Provides-Extra: dev
Requires-Dist: bandit ; extra == 'dev'
Requires-Dist: black ; extra == 'dev'
Requires-Dist: bumpver ==2023.1129 ; extra == 'dev'
Requires-Dist: coverage ~=5.0 ; extra == 'dev'
Requires-Dist: flake8 ; extra == 'dev'
Requires-Dist: pre-commit ; extra == 'dev'
